simple_structured_markup/__init__.py
simple_structured_markup/simple_structured_markup.py
simple_structured_markup-0.1.2.dist-info/LICENSE
simple_structured_markup-0.1.2.dist-info/METADATA
simple_structured_markup-0.1.2.dist-info/WHEEL
simple_structured_markup-0.1.2.dist-info/top_level.txt
simple_structured_markup-0.1.2.dist-info/RECORD
