Metadata-Version: 2.1
Name: simple_structured_markup
Version: 0.1.2
Summary: A lightweight parser for Simple Structured Markup (SSM) files.
Home-page: https://github.com/ssmlang/py
Author: sctech
Author-email: gamerselimiko@gmail.com
Classifier: Programming Language :: Python :: 3
Classifier: License :: OSI Approved :: GNU General Public License v3 or later (GPLv3+)
Classifier: Operating System :: OS Independent
Requires-Python: >=3.6
License-File: LICENSE
